LICENSE
setup.cfg
setup.py
jsonrpc_std/base.py
jsonrpc_std/error.py
jsonrpc_std/interface.py
jsonrpc_std/parse.py
jsonrpc_std.egg-info/PKG-INFO
jsonrpc_std.egg-info/SOURCES.txt
jsonrpc_std.egg-info/dependency_links.txt
jsonrpc_std.egg-info/top_level.txt