Metadata-Version: 2.1
Name: jsonrpc-std
Version: 0.1.0
Summary: Pure python standard library JSONRPC data interface
Home-page: https://gitlab.com/nolash/jsonrpc_base
Author: Louis Holbrook
Author-email: dev@holbrook.no
License: WTFPL
Keywords: jsonrpc,rpc
Platform: UNKNOWN
Classifier: Programming Language :: Python :: 3
Classifier: Operating System :: OS Independent
Classifier: Development Status :: 3 - Alpha
Classifier: Intended Audience :: Developers
Classifier: License :: OSI Approved :: GNU General Public License v3 or later (GPLv3+)
Classifier: Topic :: Software Development :: Libraries
Requires-Python: >=3.6
License-File: LICENSE
